empirica/__init__.py
empirica/api/__init__.py
empirica/api/app.py
empirica/api/routes/__init__.py
empirica/api/routes/comparison.py
empirica/api/routes/deltas.py
empirica/api/routes/heatmaps.py
empirica/api/routes/sessions.py
empirica/api/routes/verification.py
empirica/cli/__init__.py
empirica/cli/__main__.py
empirica/cli/asyncio_fix.py
empirica/cli/cli_core.py
empirica/cli/cli_utils.py
empirica/cli/simple_session_server.py
empirica/cli/uvl_formatter.py
empirica/cli/validation.py
empirica/cli/command_handlers/__init__.py
empirica/cli/command_handlers/action_commands.py
empirica/cli/command_handlers/agent_commands.py
empirica/cli/command_handlers/architecture_commands.py
empirica/cli/command_handlers/ask_handler.py
empirica/cli/command_handlers/chat_handler.py
empirica/cli/command_handlers/checkpoint_commands.py
empirica/cli/command_handlers/checkpoint_signing_commands.py
empirica/cli/command_handlers/config_commands.py
empirica/cli/command_handlers/dashboard.py
empirica/cli/command_handlers/doc_commands.py
empirica/cli/command_handlers/docs_commands.py
empirica/cli/command_handlers/edit_verification_command.py
empirica/cli/command_handlers/epistemics_commands.py
empirica/cli/command_handlers/goal_claim_command.py
empirica/cli/command_handlers/goal_commands.py
empirica/cli/command_handlers/goal_complete_command.py
empirica/cli/command_handlers/goal_discovery_commands.py
empirica/cli/command_handlers/goals_ready_command.py
empirica/cli/command_handlers/handoff_commands.py
empirica/cli/command_handlers/identity_commands.py
empirica/cli/command_handlers/investigation_commands.py
empirica/cli/command_handlers/issue_capture_commands.py
empirica/cli/command_handlers/lesson_commands.py
empirica/cli/command_handlers/mcp_commands.py
empirica/cli/command_handlers/mistake_commands.py
empirica/cli/command_handlers/modality_commands.py
empirica/cli/command_handlers/monitor_commands.py
empirica/cli/command_handlers/onboard.py
empirica/cli/command_handlers/onboard_handler.py
empirica-1.3.2.dist-info/licenses/LICENSE
empirica-1.3.2.dist-info/METADATA
empirica-1.3.2.dist-info/WHEEL
empirica-1.3.2.dist-info/entry_points.txt
empirica-1.3.2.dist-info/top_level.txt
empirica-1.3.2.dist-info/RECORD
