Metadata-Version: 2.4
Name: empirica
Version: 1.3.2
Summary: Genuine AI epistemic self-assessment framework - Universal interface for single AI tracking
Author: David S. L. Van Assche
License-Expression: MIT
Keywords: ai,llm,epistemic,self-assessment,metacognition,calibration
Classifier: Development Status :: 4 - Beta
Classifier: Intended Audience :: Developers
Classifier: Intended Audience :: Science/Research
Classifier: Operating System :: OS Independent
Classifier: Programming Language :: Python :: 3
Classifier: Programming Language :: Python :: 3.10
Classifier: Programming Language :: Python :: 3.11
Classifier: Programming Language :: Python :: 3.12
Classifier: Programming Language :: Python :: 3.13
Classifier: Topic :: Scientific/Engineering :: Artificial Intelligence
Classifier: Topic :: Software Development :: Libraries :: Python Modules
Requires-Python: >=3.10
License-File: LICENSE
Requires-Dist: pydantic>=2.0
Requires-Dist: pydantic-settings>=2.0
Requires-Dist: sqlalchemy>=2.0
Requires-Dist: pyyaml>=6.0
Requires-Dist: aiofiles>=23.0
Requires-Dist: jsonschema>=4.0
Requires-Dist: httpx>=0.24
Requires-Dist: requests>=2.31.0
Requires-Dist: cryptography>=41.0
Requires-Dist: gitpython>=3.1.0
Requires-Dist: anthropic>=0.39.0
Requires-Dist: tiktoken>=0.5.0
Requires-Dist: rich>=13.0
Requires-Dist: google-generativeai>=0.5
Requires-Dist: typer>=0.9
Provides-Extra: api
Requires-Dist: flask>=3.0; extra == "api"
Requires-Dist: flask-cors>=4.0; extra == "api"
Requires-Dist: fastapi>=0.104; extra == "api"
Requires-Dist: uvicorn>=0.24; extra == "api"
Provides-Extra: vector
Requires-Dist: qdrant-client>=1.7; extra == "vector"
Provides-Extra: vision
Requires-Dist: pytesseract>=0.3; extra == "vision"
Requires-Dist: pillow>=10.0; extra == "vision"
Requires-Dist: opencv-contrib-python>=4.8; extra == "vision"
Provides-Extra: mcp
Requires-Dist: mcp>=1.0.0; extra == "mcp"
Provides-Extra: all
Requires-Dist: empirica[api,mcp,vector,vision]; extra == "all"
Provides-Extra: test
Requires-Dist: pytest>=7.4; extra == "test"
Requires-Dist: pytest-asyncio>=0.21; extra == "test"
Requires-Dist: pytest-cov>=4.1; extra == "test"
Requires-Dist: pytest-mock>=3.11; extra == "test"
Requires-Dist: dirty-equals>=0.7; extra == "test"
Provides-Extra: lint
Requires-Dist: ruff>=0.1.0; extra == "lint"
Provides-Extra: typecheck
Requires-Dist: pyright>=1.1.330; extra == "typecheck"
Provides-Extra: dev
Requires-Dist: empirica[lint,test,typecheck]; extra == "dev"
Dynamic: license-file
